fine_python_ruff/__init__.py
fine_python_ruff/format_handler.py
fine_python_ruff/lint_handler.py
fine_python_ruff/py.typed
fine_python_ruff-0.1.0.dist-info/METADATA
fine_python_ruff-0.1.0.dist-info/WHEEL
fine_python_ruff-0.1.0.dist-info/top_level.txt
fine_python_ruff-0.1.0.dist-info/RECORD
