Metadata-Version: 2.4
Name: fine_python_ruff
Version: 0.1.0
Author-email: Vladyslav Hnatiuk <aders1234@gmail.com>
Requires-Python: <3.14,>=3.11
Requires-Dist: finecode_extension_api==0.3.*
Requires-Dist: ruff<1.0.0,>=0.8.0
